rpmautospec/__init__.py
rpmautospec/changelog.py
rpmautospec/compat.py
rpmautospec/exc.py
rpmautospec/magic_comments.py
rpmautospec/pkg_history.py
rpmautospec/util.py
rpmautospec/version.py
rpmautospec/_wrappers/__init__.py
rpmautospec/_wrappers/common.py
rpmautospec/_wrappers/minigit2/__init__.py
rpmautospec/_wrappers/minigit2/blob.py
rpmautospec/_wrappers/minigit2/branch.py
rpmautospec/_wrappers/minigit2/commit.py
rpmautospec/_wrappers/minigit2/config.py
rpmautospec/_wrappers/minigit2/constants.py
rpmautospec/_wrappers/minigit2/diff.py
rpmautospec/_wrappers/minigit2/enums.py
rpmautospec/_wrappers/minigit2/exc.py
rpmautospec/_wrappers/minigit2/index.py
rpmautospec/_wrappers/minigit2/native_adaptation.py
rpmautospec/_wrappers/minigit2/object_.py
rpmautospec/_wrappers/minigit2/oid.py
rpmautospec/_wrappers/minigit2/reference.py
rpmautospec/_wrappers/minigit2/repository.py
rpmautospec/_wrappers/minigit2/revwalk.py
rpmautospec/_wrappers/minigit2/settings.py
rpmautospec/_wrappers/minigit2/signature.py
rpmautospec/_wrappers/minigit2/tag.py
rpmautospec/_wrappers/minigit2/tree.py
rpmautospec/_wrappers/minigit2/wrapper.py
rpmautospec/_wrappers/minirpm/__init__.py
rpmautospec/_wrappers/minirpm/_rpm/__init__.py
rpmautospec/_wrappers/minirpm/_rpm/exc.py
rpmautospec/_wrappers/minirpm/_rpm/header.py
rpmautospec/_wrappers/minirpm/_rpm/native_adaptation.py
rpmautospec/_wrappers/minirpm/_rpm/spec.py
rpmautospec/_wrappers/minirpm/_rpm/toplevel.py
rpmautospec/cli/__init__.py
rpmautospec/cli/base.py
rpmautospec/cli/click.py
rpmautospec/cli/dispatch.py
rpmautospec/cli/minimal.py
rpmautospec/cli/pager.py
rpmautospec/subcommands/__init__.py
rpmautospec/subcommands/changelog.py
rpmautospec/subcommands/convert.py
rpmautospec/subcommands/process_distgit.py
rpmautospec/subcommands/release.py
rpmautospec-0.8.3.dist-info/METADATA
rpmautospec-0.8.3.dist-info/WHEEL
rpmautospec-0.8.3.dist-info/entry_points.txt
rpmautospec-0.8.3.dist-info/licenses/licenses/LICENSE.GPLv2
rpmautospec-0.8.3.dist-info/licenses/licenses/LICENSE.MIT
rpmautospec-0.8.3.dist-info/RECORD
