Metadata-Version: 2.4
Name: rpmautospec
Version: 0.8.3
Summary: A package and CLI tool to generate RPM release fields and changelogs.
Project-URL: repository, https://github.com/fedora-infra/rpmautospec
Author-email: Pierre-Yves Chibon <pingou@pingoured.fr>, Nils Philippsen <nils@redhat.com>, Adam Saleh <asaleh@redhat.com>, Stephen Coady <scoady@redhat.com>, David Kirwan <dkirwan@redhat.com>, Elliott Sales de Andrade <quantum.analyst@gmail.com>, Zbigniew Jędrzejewski-Szmek <zbyszek@in.waw.pl>, Miro Hrončok <miro@hroncok.cz>
Maintainer-email: Fedora Infrastructure <admin@fedoraproject.org>
License-Expression: MIT AND GPL-2.0-only WITH GCC-exception-2.0 AND (MIT OR GPL-2.0-or-later WITH GCC-exception-2.0)
License-File: licenses/LICENSE.GPLv2
License-File: licenses/LICENSE.MIT
Requires-Python: <4.0,>=3.9
Requires-Dist: rpmautospec-core<1.0.0,>=0.1.4
Provides-Extra: all
Requires-Dist: click<9,>=8; extra == 'all'
Requires-Dist: pygit2<1.18.3,>=1.4.0; (python_full_version >= '3.9.0' and python_full_version < '3.10.0') and extra == 'all'
Requires-Dist: pygit2<2.0.0,>=1.4.0; (python_full_version >= '3.10.0' and python_full_version < '4.0.0') and extra == 'all'
Requires-Dist: rpm; extra == 'all'
Provides-Extra: click
Requires-Dist: click<9,>=8; extra == 'click'
Provides-Extra: pygit2
Requires-Dist: pygit2<1.18.3,>=1.4.0; (python_full_version >= '3.9.0' and python_full_version < '3.10.0') and extra == 'pygit2'
Requires-Dist: pygit2<2.0.0,>=1.4.0; (python_full_version >= '3.10.0' and python_full_version < '4.0.0') and extra == 'pygit2'
Provides-Extra: rpm
Requires-Dist: rpm; extra == 'rpm'
